Workbook
Name NativeTimeline_Date: #N/A
Name Slicer_Category1: #N/A
Name Slicer_Payment_Mode1: #N/A
Name Slicer_Region: #N/A

Sheet Sales_Data
A1: Order_ID | B1: Date | C1: Region | D1: Customer | E1: Category | F1: Sub-Category | G1: Product | H1: Quantity | I1: Unit Price | J1: Discount % | K1: Sales | L1: Cost | M1: Payment Mode | N1: Month | O1: Quater | P1: Discount Value | Q1: Net Sales | R1: Profit | S1: Profit% | T1: Sales Value
A2: ORD0001 | B2: 45386 | C2: East | D2: Zoya Khan | E2: Electronics | F2: Laptop | G2: Asus VivoBook | H2: 1 | I2: 84888 | J2: 0.12 | K2: 74701.44 | L2: 65672.43 | M2: UPI | N2: =TEXT(B2,"mmmm") -> April | O2: =ROUNDUP(MONTH(B2)/3,0) -> 2 | P2: =K2*J2 -> 8964.1728 | Q2: =K2-P2 -> 65737.267 | R2: =K2-L2 -> 9029.01 | S2: =R2/K2*100 -> 12.086795 | T2: =IF(K2>30000,"High",IF(K2>10000,"Medium","Low")) -> High
A3: ORD0002 | B3: 45564 | C3: West | D3: Suresh Kumar | E3: Clothing | F3: Kids | G3: Kids T-shirt | H3: 4 | I3: 84951 | J3: 0.15 | K3: 288833.4 | L3: 245445.54 | M3: UPI | N3: =TEXT(B3,"mmmm") -> September | O3: =ROUNDUP(MONTH(B3)/3,0) -> 3 | P3: =K3*J3 -> 43325.01 | Q3: =K3-P3 -> 245508.39 | R3: =K3-L3 -> 43387.86 | S3: =R3/K3*100 -> 15.02176 | T3: =IF(K3>30000,"High",IF(K3>10000,"Medium","Low")) -> High
A4: ORD0003 | B4: 45028 | C4: South | D4: Simran Kaur | E4: Electronics | F4: Mobile | G4: OnePlus | H4: 1 | I4: 80258 | J4: 0.08 | K4: 73837.36 | L4: 56140.31 | M4: UPI | N4: =TEXT(B4,"mmmm") -> April | O4: =ROUNDUP(MONTH(B4)/3,0) -> 2 | P4: =K4*J4 -> 5906.9888 | Q4: =K4-P4 -> 67930.371 | R4: =K4-L4 -> 17697.05 | S4: =R4/K4*100 -> 23.967609 | T4: =IF(K4>30000,"High",IF(K4>10000,"Medium","Low")) -> High
A5: ORD0004 | B5: 45464 | C5: East | D5: Suresh Kumar | E5: Furniture | F5: Table | G5: Coffee Table | H5: 2 | I5: 39663 | J5: 0.05 | K5: 75359.7 | L5: 65309.28 | M5: Card | N5: =TEXT(B5,"mmmm") -> June | O5: =ROUNDUP(MONTH(B5)/3,0) -> 2 | P5: =K5*J5 -> 3767.985 | Q5: =K5-P5 -> 71591.715 | R5: =K5-L5 -> 10050.42 | S5: =R5/K5*100 -> 13.336598 | T5: =IF(K5>30000,"High",IF(K5>10000,"Medium","Low")) -> High
A6: ORD0005 | B6: 45324 | C6: North | D6: Manish Pandey | E6: Electronics | F6: Accessories | G6: Power Bank | H6: 4 | I6: 45866 | J6: 0.15 | K6: 155944.4 | L6: 117706.77 | M6: UPI | N6: =TEXT(B6,"mmmm") -> February | O6: =ROUNDUP(MONTH(B6)/3,0) -> 1 | P6: =K6*J6 -> 23391.66 | Q6: =K6-P6 -> 132552.74 | R6: =K6-L6 -> 38237.63 | S6: =R6/K6*100 -> 24.52004 | T6: =IF(K6>30000,"High",IF(K6>10000,"Medium","Low")) -> High
A7: ORD0006 | B7: 45170 | C7: West | D7: Neha Verma | E7: Furniture | F7: Sofa | G7: 3-Seater Sofa | H7: 1 | I7: 34884 | J7: 0.05 | K7: 33139.8 | L7: 29769.3 | M7: Card | N7: =TEXT(B7,"mmmm") -> September | O7: =ROUNDUP(MONTH(B7)/3,0) -> 3 | P7: =K7*J7 -> 1656.99 | Q7: =K7-P7 -> 31482.81 | R7: =K7-L7 -> 3370.5 | S7: =R7/K7*100 -> 10.17055 | T7: =IF(K7>30000,"High",IF(K7>10000,"Medium","Low")) -> High
A8: ORD0007 | B8: 45136 | C8: North | D8: Anita Joshi | E8: Furniture | F8: Sofa | G8: 3-Seater Sofa | H8: 3 | I8: 81588 | J8: 0.08 | K8: 225182.88 | L8: 192579.34 | M8: Card | N8: =TEXT(B8,"mmmm") -> July | O8: =ROUNDUP(MONTH(B8)/3,0) -> 3 | P8: =K8*J8 -> 18014.63 | Q8: =K8-P8 -> 207168.25 | R8: =K8-L8 -> 32603.54 | S8: =R8/K8*100 -> 14.478694 | T8: =IF(K8>30000,"High",IF(K8>10000,"Medium","Low")) -> High
A9: ORD0008 | B9: 45074 | C9: East | D9: Priya Nair | E9: Clothing | F9: Men | G9: Shirt | H9: 1 | I9: 82522 | J9: 0 | K9: 82522 | L9: 66861.42 | M9: Cash | N9: =TEXT(B9,"mmmm") -> May | O9: =ROUNDUP(MONTH(B9)/3,0) -> 2 | P9: =K9*J9 -> 0 | Q9: =K9-P9 -> 82522 | R9: =K9-L9 -> 15660.58 | S9: =R9/K9*100 -> 18.977461 | T9: =IF(K9>30000,"High",IF(K9>10000,"Medium","Low")) -> High
A10: ORD0009 | B10: 44952 | C10: South | D10: Zoya Khan | E10: Clothing | F10: Women | G10: Saree | H10: 1 | I10: 16391 | J10: 0 | K10: 16391 | L10: 14398.35 | M10: Card | N10: =TEXT(B10,"mmmm") -> January | O10: =ROUNDUP(MONTH(B10)/3,0) -> 1 | P10: =K10*J10 -> 0 | Q10: =K10-P10 -> 16391 | R10: =K10-L10 -> 1992.65 | S10: =R10/K10*100 -> 12.156976 | T10: =IF(K10>30000,"High",IF(K10>10000,"Medium","Low")) -> Medium
A11: ORD0010 | B11: 45420 | C11: West | D11: Aditya Mehta | E11: Electronics | F11: Mobile | G11: Samsung | H11: 3 | I11: 25722 | J11: 0.08 | K11: 70992.72 | L11: 55978.39 | M11: Cash | N11: =TEXT(B11,"mmmm") -> May | O11: =ROUNDUP(MONTH(B11)/3,0) -> 2 | P11: =K11*J11 -> 5679.4176 | Q11: =K11-P11 -> 65313.302 | R11: =K11-L11 -> 15014.33 | S11: =R11/K11*100 -> 21.149112 | T11: =IF(K11>30000,"High",IF(K11>10000,"Medium","Low")) -> High
A12: ORD0011 | B12: 45549 | C12: South | D12: Neha Verma | E12: Electronics | F12: Laptop | G12: Asus VivoBook | H12: 4 | I12: 67745 | J12: 0.1 | K12: 243882 | L12: 198430.78 | M12: UPI | N12: =TEXT(B12,"mmmm") -> September | O12: =ROUNDUP(MONTH(B12)/3,0) -> 3 | P12: =K12*J12 -> 24388.2 | Q12: =K12-P12 -> 219493.8 | R12: =K12-L12 -> 45451.22 | S12: =R12/K12*100 -> 18.636562 | T12: =IF(K12>30000,"High",IF(K12>10000,"Medium","Low")) -> High
A13: ORD0012 | B13: 44934 | C13: South | D13: Aditya Mehta | E13: Furniture | F13: Bed | G13: Queen Bed | H13: 3 | I13: 18507 | J13: 0.08 | K13: 51079.32 | L13: 45029.08 | M13: Card | N13: =TEXT(B13,"mmmm") -> January | O13: =ROUNDUP(MONTH(B13)/3,0) -> 1 | P13: =K13*J13 -> 4086.3456 | Q13: =K13-P13 -> 46992.974 | R13: =K13-L13 -> 6050.24 | S13: =R13/K13*100 -> 11.844794 | T13: =IF(K13>30000,"High",IF(K13>10000,"Medium","Low")) -> High
... A2001: ORD2000 | B2001: 45251 | C2001: East | D2001: Simran Kaur | E2001: Clothing | F2001: Women | G2001: Dress | H2001: 4 | I2001: 57237 | J2001: 0 | K2001: 228948 | L2001: 183837.31 | M2001: UPI | N2001: =TEXT(B2001,"mmmm") -> November | O2001: =ROUNDUP(MONTH(B2001)/3,0) -> 4 | P2001: =K2001*J2001 -> 0 | Q2001: =K2001-P2001 -> 228948 | R2001: =K2001-L2001 -> 45110.69 | S2001: =R2001/K2001*100 -> 19.703465 | T2001: =IF(K2001>30000,"High",IF(K2001>10000,"Medium","Low")) -> High

Sheet dashboard
D5: Row Labels | E5: Sum of Sales | G5: Category | H5: Sum of Sales | L5: Sum of Sales
D6: East | E6: 65329595 | G6: Clothing | H6: 82282162 | L6: 2.4597736e+08
D7: North | E7: 58601932 | G7: Kids | H7: 24951610
D8: South | E8: 61634578 | G8: Men | H8: 28834627
D9: West | E9: 60411258 | G9: Women | H9: 28495925
D10: Grand Total | E10: 2.4597736e+08 | G10: Electronics | H10: 81691151 | L10: Sum of Profit
G11: Accessories | H11: 29818691 | L11: 43274159
D12: Customer | E12: Total Spent | G12: Laptop | H12: 25408066
D13: Aditya Mehta | E13: 22072659 | G13: Mobile | H13: 26464394
D14: Anita Joshi | E14: 21313356 | G14: Furniture | H14: 82004049
D15: Arjun Singh | E15: 17989246 | G15: Bed | H15: 23809441 | L15: Sum of Quantity
D16: Harsh Patel | E16: 18469483 | G16: Chair | H16: 18985088 | L16: 5929
D17: Kavita Rao | E17: 14166978 | G17: Sofa | H17: 19099379
D18: Manish Pandey | E18: 19097498 | G18: Table | H18: 20110141
D19: Neha Verma | E19: 14560304 | G19: Grand Total | H19: 2.4597736e+08
D20: Priya Nair | E20: 16161254
D21: Rakesh Jain | E21: 15703502
D22: Riya Jain | E22: 14524049 | G22: Row Labels | H22: Sum of Profit
D23: Rohan Sharma | E23: 16060672 | G23: Clothing | H23: 14450948
D24: Simran Kaur | E24: 16955055 | G24: Electronics | H24: 14295623
D25: Suresh Kumar | E25: 18908744 | G25: Furniture | H25: 14527588
D26: Zoya Khan | E26: 19994562 | G26: Grand Total | H26: 43274159
D27: Grand Total | E27: 2.4597736e+08

Sheet Formula
A1: Region | B1: Total Sales
A2: North | B2: =SUMIF(Sales_Data!C2:C2001,Formula!A2,Sales_Data!K2:K2001) -> 58601932
A4: Mode | B4: Order(countif)
A5: UPI | B5: =COUNTIF(Sales_Data!M2:M2001,Formula!A5) -> 668
A7: Average Sales
A8: =AVERAGE(Sales_Data!K2:K2001) -> 122988.68
A10: Costumer who perchase higher product
A11: =_xlfn.XLOOKUP(MAX(Sales_Data!K2:K2001),Sales_Data!K2:K2001,Sales_Data!D2:D2001) -> Rohan Sharma
A14: Costumer | B14: Total Sales | C14: Costumer | D14: purchase
A15: {=_xlfn.UNIQUE(Sales_Data!D2:D2001)} -> Zoya Khan | B15: =SUMIF(Sales_Data!D2:D2001,Formula!A15,Sales_Data!K2:K2001) -> 19994562 | C15: Aditya Mehta | D15: 22072659
A16: Suresh Kumar | B16: =SUMIF(Sales_Data!D3:D2002,Formula!A16,Sales_Data!K3:K2002) -> 18908744 | C16: Anita Joshi | D16: 21313356
A17: Simran Kaur | B17: =SUMIF(Sales_Data!D4:D2003,Formula!A17,Sales_Data!K4:K2003) -> 16955055 | C17: Zoya Khan | D17: 19994562
A18: Manish Pandey | B18: =SUMIF(Sales_Data!D5:D2004,Formula!A18,Sales_Data!K5:K2004) -> 19097498 | C18: Manish Pandey | D18: 19097498
A19: Neha Verma | B19: =SUMIF(Sales_Data!D6:D2005,Formula!A19,Sales_Data!K6:K2005) -> 14560304 | C19: Suresh Kumar | D19: 18908744
A20: Anita Joshi | B20: =SUMIF(Sales_Data!D7:D2006,Formula!A20,Sales_Data!K7:K2006) -> 21313356 | C20: Harsh Patel | D20: 18469483
A21: Priya Nair | B21: =SUMIF(Sales_Data!D8:D2007,Formula!A21,Sales_Data!K8:K2007) -> 16161254 | C21: Arjun Singh | D21: 17989246
A22: Aditya Mehta | B22: =SUMIF(Sales_Data!D9:D2008,Formula!A22,Sales_Data!K9:K2008) -> 22072659 | C22: Simran Kaur | D22: 16955055
A23: Kavita Rao | B23: =SUMIF(Sales_Data!D10:D2009,Formula!A23,Sales_Data!K10:K2009) -> 14166978 | C23: Priya Nair | D23: 16161254
A24: Riya Jain | B24: =SUMIF(Sales_Data!D11:D2010,Formula!A24,Sales_Data!K11:K2010) -> 14524049 | C24: Rohan Sharma | D24: 16060672
A25: Arjun Singh | B25: =SUMIF(Sales_Data!D12:D2011,Formula!A25,Sales_Data!K12:K2011) -> 17989246 | C25: Rakesh Jain | D25: 15703502
A26: Rakesh Jain | B26: =SUMIF(Sales_Data!D13:D2012,Formula!A26,Sales_Data!K13:K2012) -> 15703502 | C26: Neha Verma | D26: 14560304
A27: Rohan Sharma | B27: =SUMIF(Sales_Data!D14:D2013,Formula!A27,Sales_Data!K14:K2013) -> 16060672 | C27: Riya Jain | D27: 14524049
A28: Harsh Patel | B28: =SUMIF(Sales_Data!D15:D2014,Formula!A28,Sales_Data!K15:K2014) -> 18469483 | C28: Kavita Rao | D28: 14166978
A31: Region | B31: Dropdown1 | C31: Dropdown2
A32: {=_xlfn.UNIQUE(Sales_Data!C2:C2001)} -> East
A33: West
A34: South
A35: North

Sheet order per region
A1: North
A2: {=_xlfn._xlws.FILTER(Sales_Data!A2:T2001,Sales_Data!C2:C2001=A1)} -> ORD0005 | B2: 45324 | C2: North | D2: Manish Pandey | E2: Electronics | F2: Accessories | G2: Power Bank | H2: 4 | I2: 45866 | J2: 0.15 | K2: 155944.4 | L2: 117706.77 | M2: UPI | N2: February | O2: 1 | P2: 23391.66 | Q2: 132552.74 | R2: 38237.63 | S2: 24.52004 | T2: High
A3: ORD0007 | B3: 45136 | C3: North | D3: Anita Joshi | E3: Furniture | F3: Sofa | G3: 3-Seater Sofa | H3: 3 | I3: 81588 | J3: 0.08 | K3: 225182.88 | L3: 192579.34 | M3: Card | N3: July | O3: 3 | P3: 18014.63 | Q3: 207168.25 | R3: 32603.54 | S3: 14.478694 | T3: High
A4: ORD0019 | B4: 45595 | C4: North | D4: Priya Nair | E4: Electronics | F4: Mobile | G4: Oppo | H4: 4 | I4: 14099 | J4: 0.08 | K4: 51884.32 | L4: 43587.66 | M4: Cash | N4: October | O4: 4 | P4: 4150.7456 | Q4: 47733.574 | R4: 8296.66 | S4: 15.990689 | T4: High
A5: ORD0025 | B5: 45626 | C5: North | D5: Zoya Khan | E5: Electronics | F5: Mobile | G5: iPhone | H5: 5 | I5: 15178 | J5: 0.1 | K5: 68301 | L5: 52450.02 | M5: Card | N5: November | O5: 4 | P5: 6830.1 | Q5: 61470.9 | R5: 15850.98 | S5: 23.207537 | T5: High
A6: ORD0027 | B6: 45256 | C6: North | D6: Rakesh Jain | E6: Furniture | F6: Chair | G6: Wooden Chair | H6: 2 | I6: 67456 | J6: 0.15 | K6: 114675.2 | L6: 86692.21 | M6: Card | N6: November | O6: 4 | P6: 17201.28 | Q6: 97473.92 | R6: 27982.99 | S6: 24.401954 | T6: High
A7: ORD0031 | B7: 45463 | C7: North | D7: Arjun Singh | E7: Clothing | F7: Men | G7: Jeans | H7: 2 | I7: 26495 | J7: 0.12 | K7: 46631.2 | L7: 39671.4 | M7: Cash | N7: June | O7: 2 | P7: 5595.744 | Q7: 41035.456 | R7: 6959.8 | S7: 14.9252 | T7: High
A8: ORD0032 | B8: 45184 | C8: North | D8: Kavita Rao | E8: Clothing | F8: Women | G8: Saree | H8: 2 | I8: 87830 | J8: 0.08 | K8: 161607.2 | L8: 135646.75 | M8: Cash | N8: September | O8: 3 | P8: 12928.576 | Q8: 148678.62 | R8: 25960.45 | S8: 16.063919 | T8: High
A9: ORD0034 | B9: 45440 | C9: North | D9: Manish Pandey | E9: Furniture | F9: Bed | G9: King Size Bed | H9: 3 | I9: 86624 | J9: 0.12 | K9: 228687.36 | L9: 194095.35 | M9: Cash | N9: May | O9: 2 | P9: 27442.483 | Q9: 201244.88 | R9: 34592.01 | S9: 15.126332 | T9: High
A10: ORD0038 | B10: 45415 | C10: North | D10: Aditya Mehta | E10: Clothing | F10: Kids | G10: Kids Jacket | H10: 4 | I10: 41150 | J10: 0.15 | K10: 139910 | L10: 119235.66 | M10: UPI | N10: May | O10: 2 | P10: 20986.5 | Q10: 118923.5 | R10: 20674.34 | S10: 14.776885 | T10: High
A11: ORD0042 | B11: 45474 | C11: North | D11: Anita Joshi | E11: Furniture | F11: Chair | G11: Office Chair | H11: 4 | I11: 31626 | J11: 0.05 | K11: 120178.8 | L11: 103899.46 | M11: Cash | N11: July | O11: 3 | P11: 6008.94 | Q11: 114169.86 | R11: 16279.34 | S11: 13.545933 | T11: High
A12: ORD0043 | B12: 45017 | C12: North | D12: Simran Kaur | E12: Furniture | F12: Bed | G12: King Size Bed | H12: 1 | I12: 38039 | J12: 0.05 | K12: 36137.05 | L12: 29941.13 | M12: UPI | N12: April | O12: 2 | P12: 1806.8525 | Q12: 34330.198 | R12: 6195.92 | S12: 17.145616 | T12: High
A13: ORD0046 | B13: 45434 | C13: North | D13: Rohan Sharma | E13: Electronics | F13: Accessories | G13: Power Bank | H13: 1 | I13: 15743 | J13: 0.12 | K13: 13853.84 | L13: 11119.66 | M13: Cash | N13: May | O13: 2 | P13: 1662.4608 | Q13: 12191.379 | R13: 2734.18 | S13: 19.7359 | T13: Medium
A14: ORD0049 | B14: 45020 | C14: North | D14: Manish Pandey | E14: Electronics | F14: Accessories | G14: Power Bank | H14: 5 | I14: 57700 | J14: 0.15 | K14: 245225 | L14: 196236.76 | M14: Card | N14: April | O14: 2 | P14: 36783.75 | Q14: 208441.25 | R14: 48988.24 | S14: 19.976854 | T14: High
... A475: ORD1998 | B475: 45343 | C475: North | D475: Manish Pandey | E475: Electronics | F475: Laptop | G475: Dell Inspiron | H475: 3 | I475: 70224 | J475: 0.15 | K475: 179071.2 | L475: 151648.55 | M475: Card | N475: February | O475: 1 | P475: 26860.68 | Q475: 152210.52 | R475: 27422.65 | S475: 15.313825 | T475: High

Sheet pivote table
A3: Row Labels | B3: Sum of Sales | D3: Row Labels | E3: Sum of Profit | G3: Row Labels | H3: Sum of Sales | J3: Row Labels | K3: Sum of Sales | M3: Row Labels | N3: Sum of Sales
A4: East | B4: 65329595 | D4: Clothing | E4: 14450948 | G4: Aditya Mehta | H4: 22072659 | J4: Jan | K4: 23825599 | M4: Clothing | N4: 82282162
A5: North | B5: 58601932 | D5: Electronics | E5: 14295623 | G5: Anita Joshi | H5: 21313356 | J5: Feb | K5: 19079702 | M5: Kids | N5: 24951610
A6: South | B6: 61634578 | D6: Furniture | E6: 14527588 | G6: Arjun Singh | H6: 17989246 | J6: Mar | K6: 19725414 | M6: Men | N6: 28834627 | U6: Sum of Sales | X6: Sum of Profit | AA6: Sum of Quantity
A7: West | B7: 60411258 | D7: Grand Total | E7: 43274159 | G7: Harsh Patel | H7: 18469483 | J7: Apr | K7: 20247145 | M7: Women | N7: 28495925 | U7: 2.4597736e+08 | X7: 43274159 | AA7: 5929
A8: Grand Total | B8: 2.4597736e+08 | G8: Kavita Rao | H8: 14166978 | J8: May | K8: 21292890 | M8: Electronics | N8: 81691151
G9: Manish Pandey | H9: 19097498 | J9: Jun | K9: 17246615 | M9: Accessories | N9: 29818691
G10: Neha Verma | H10: 14560304 | J10: Jul | K10: 20452699 | M10: Laptop | N10: 25408066
G11: Priya Nair | H11: 16161254 | J11: Aug | K11: 21669374 | M11: Mobile | N11: 26464394
G12: Rakesh Jain | H12: 15703502 | J12: Sep | K12: 18767980 | M12: Furniture | N12: 82004049
G13: Riya Jain | H13: 14524049 | J13: Oct | K13: 21558062 | M13: Bed | N13: 23809441
G14: Rohan Sharma | H14: 16060672 | J14: Nov | K14: 20324208 | M14: Chair | N14: 18985088
G15: Simran Kaur | H15: 16955055 | J15: Dec | K15: 21787674 | M15: Sofa | N15: 19099379
G16: Suresh Kumar | H16: 18908744 | J16: Grand Total | K16: 2.4597736e+08 | M16: Table | N16: 20110141
G17: Zoya Khan | H17: 19994562 | M17: Grand Total | N17: 2.4597736e+08
G18: Grand Total | H18: 2.4597736e+08

Sheet chart
A2: line chart | J2: bar chart
